setup.py
stat_distrib/Binomialdistribution.py
stat_distrib/Gaussiandistribution.py
stat_distrib/Generaldistribution.py
stat_distrib/__init__.py
stat_distrib.egg-info/PKG-INFO
stat_distrib.egg-info/SOURCES.txt
stat_distrib.egg-info/dependency_links.txt
stat_distrib.egg-info/not-zip-safe
stat_distrib.egg-info/top_level.txt