Metadata-Version: 1.0
Name: stat-distrib
Version: 0.1
Summary: Simple Distributions
Home-page: UNKNOWN
Author: UNKNOWN
Author-email: UNKNOWN
License: UNKNOWN
Platform: UNKNOWN
